{
  "version": 1,
  "deckId": "round_3_normal_a",
  "name": "外卖骑手",
  "description": "第3轮｜切磋｜风格：激进｜外卖、抢单、差评核心",
  "aiStyle": "aggressive",
  "cardIds": [
    1,
    1,
    1,
    1,
    1,
    1,
    1,
    6,
    39,
    39,
    40,
    40,
    41,
    41,
    41,
    0,
    0,
    0,
    0,
    0
  ],
  "opponentLines": {
    "matchStart": [
      "我没时间慢慢算，慢了就什么都没了。",
      "这一单必须送到，别挡路。",
      "倒计时还在跳，开牌。"
    ],
    "matchVictory": [
      "压哨送到，系统没扣我。",
      "看见没？只要够快，就还有路。"
    ],
    "matchDefeat": [
      "超时了……这下真的完了。",
      "我已经骑到最快了，怎么还是不够。"
    ],
    "onDraw": [
      "再抢一单。",
      "油门别松。",
      "差评别来，求你了。"
    ],
    "roundWin": [
      "这一局，刚好赶上。",
      "红灯前过去了。"
    ],
    "roundLose": [
      "路线错了，绕不回来了。",
      "这一单扣钱，比输还疼。"
    ]
  }
}
